hopscotch/__init__.py
hopscotch/callers.py
hopscotch/field_infos.py
hopscotch/operators.py
hopscotch/py.typed
hopscotch/registry.py
hopscotch/version.py
hopscotch/fixtures/__init__.py
hopscotch/fixtures/dataklasses.py
hopscotch/fixtures/functions.py
hopscotch/fixtures/named_tuples.py
hopscotch/fixtures/plain_classes.py
hopscotch/fixtures/hopscotch_setup/__init__.py
hopscotch/fixtures/init_caller_package/__init__.py
hopscotch-0.3.2.dist-info/METADATA
hopscotch-0.3.2.dist-info/WHEEL
hopscotch-0.3.2.dist-info/licenses/LICENSE.md
hopscotch-0.3.2.dist-info/RECORD
