Metadata-Version: 2.1
Name: hopscotch
Version: 0.3.2
Summary: Type-oriented registry with dependency injection.
Author-email: Paul Everitt <pauleveritt@me.com>
License-Expression: MIT
License-File: LICENSE.md
Classifier: Programming Language :: Python :: 3.11
Classifier: Programming Language :: Python :: 3.12
Requires-Python: >=3.11
Requires-Dist: venusian~=3.1.0
